setup.py
shareabouts/__init__.py
shareabouts/api.py
shareabouts/exceptions.py
shareabouts/models.py
shareabouts.egg-info/PKG-INFO
shareabouts.egg-info/SOURCES.txt
shareabouts.egg-info/dependency_links.txt
shareabouts.egg-info/requires.txt
shareabouts.egg-info/top_level.txt