Metadata-Version: 1.0
Name: shareabouts
Version: 0.1.0
Summary: A Python adapter for the Shareabouts API
Home-page: https://github.com/openplans/pyshareabouts
Author: Mjumbe Poe
Author-email: mpoe@openplans.org
License: BSD
Platform: UNKNOWN
